hypothesis_requests/__init__.py
hypothesis_requests/strategies/__init__.py
hypothesis_requests/strategies/exceptions.py
hypothesis_requests/strategies/request.py
hypothesis_requests/strategies/response.py
hypothesis_requests/strategies/session.py
hypothesis_requests-0.1.0.dist-info/LICENSE
hypothesis_requests-0.1.0.dist-info/WHEEL
hypothesis_requests-0.1.0.dist-info/METADATA
hypothesis_requests-0.1.0.dist-info/RECORD
